{
  "gitlens.codeLens.enabled": false,
  "editor.formatOnSave": true,
  "editor.trimAutoWhitespace": true,
  "files.trimFinalNewlines": true,
  "files.insertFinalNewline": true,
  "files.trimTrailingWhitespace": true,
  "editor.fontFamily": "'Hack', 'Droid Sans Mono', 'monospace', monospace, 'Droid Sans Fallback'",
  "editor.fontSize": 12,
  "editor.renderWhitespace": "none",
  "editor.rulers": [
    79,
    120
  ],
  "terminal.integrated.fontFamily": "Hack",
  "python.formatting.provider": "black",
  "python.formatting.blackPath": "~/.local/bin/black",
  "python.linting.pylintPath": "~/.local/bin/pylint",
  "python.linting.flake8Enabled": true,
  "python.linting.flake8Path": "~/.local/bin/flake8",
  "python.linting.mypyEnabled": true,
  "python.linting.mypyPath": "~/.local/bin/mypy",
  "python.linting.banditEnabled": true,
  "python.linting.banditPath": "~/.local/bin/bandit",
  "workbench.iconTheme": "material-icon-theme",
  "workbench.colorTheme": "Monokai Pro (Filter Spectrum)",
  "javascript.updateImportsOnFileMove.enabled": "always",
  "autoDocstring.docstringFormat": "google"
}
